pulp_ansible/__init__.py
pulp_ansible/pytest_plugin.py
pulp_ansible/app/__init__.py
pulp_ansible/app/constants.py
pulp_ansible/app/downloaders.py
pulp_ansible/app/fields.py
pulp_ansible/app/global_access_conditions.py
pulp_ansible/app/logutils.py
pulp_ansible/app/modelresource.py
pulp_ansible/app/models.py
pulp_ansible/app/serializers.py
pulp_ansible/app/settings.py
pulp_ansible/app/urls.py
pulp_ansible/app/utils.py
pulp_ansible/app/viewsets.py
pulp_ansible/app/galaxy/__init__.py
pulp_ansible/app/galaxy/mixins.py
pulp_ansible/app/galaxy/serializers.py
pulp_ansible/app/galaxy/views.py
pulp_ansible/app/galaxy/v3/__init__.py
pulp_ansible/app/galaxy/v3/exceptions.py
pulp_ansible/app/galaxy/v3/filters.py
pulp_ansible/app/galaxy/v3/pagination.py
pulp_ansible/app/galaxy/v3/serializers.py
pulp_ansible/app/galaxy/v3/views.py
pulp_ansible/app/galaxy/v3/viewsets.py
pulp_ansible/app/management/__init__.py
pulp_ansible/app/management/commands/__init__.py
pulp_ansible/app/management/commands/download-log.py
pulp_ansible/app/migrations/0001_initial.py
pulp_ansible/app/migrations/0001_initial_squashed_0040_ansiblerepository_keyring.py
pulp_ansible/app/migrations/0002_advanced_collections.py
pulp_ansible/app/migrations/0003_add_tags_and_collectionversion_fields.py
pulp_ansible/app/migrations/0004_add_fulltext_search_indexes.py
pulp_ansible/app/migrations/0005_collectionversion_is_highest.py
pulp_ansible/app/migrations/0006_remove_whitelist_and_alter_collection_version_name.py
pulp_ansible/app/migrations/0007_collectionversion_is_certified.py
pulp_ansible/app/migrations/0008_collectionremote_requirements_file.py
pulp_ansible/app/migrations/0009_collectionimport.py
pulp_ansible/app/migrations/0010_ansible_related_names.py
pulp_ansible/app/migrations/0011_collectionimport.py
pulp_ansible/app/migrations/0012_auto_20190906_2253.py
pulp_ansible/app/migrations/0013_pulp_fields.py
pulp_ansible/app/migrations/0014_certification_enum.py
pulp_ansible/app/migrations/0015_ansiblerepository.py
pulp_ansible-0.29.0.dist-info/licenses/LICENSE
pulp_ansible-0.29.0.dist-info/METADATA
pulp_ansible-0.29.0.dist-info/WHEEL
pulp_ansible-0.29.0.dist-info/entry_points.txt
pulp_ansible-0.29.0.dist-info/top_level.txt
pulp_ansible-0.29.0.dist-info/RECORD
