Metadata-Version: 2.4
Name: pulp-ansible
Version: 0.29.0
Summary: Pulp plugin to manage Ansible content, e.g. roles
Author-email: Pulp Ansible Plugin Project Developers <pulp-dev@redhat.com>
Project-URL: Homepage, https://pulpproject.org
Project-URL: Documentation, https://pulpproject.org/pulp_ansible/
Project-URL: Repository, https://github.com/pulp/pulp_ansible
Project-URL: Bug Tracker, https://github.com/pulp/pulp_ansible/issues
Project-URL: Changelog, https://pulpproject.org/pulp_ansible/changes/
Classifier: License :: OSI Approved :: GNU General Public License v2 or later (GPLv2+)
Classifier: Operating System :: POSIX :: Linux
Classifier: Development Status :: 5 - Production/Stable
Classifier: Framework :: Django
Classifier: Programming Language :: Python
Classifier: Programming Language :: Python :: 3
Requires-Python: >=3.11
License-File: LICENSE
Requires-Dist: galaxy_importer<0.5,>=0.4.27
Requires-Dist: GitPython<3.2,>=3.1.24
Requires-Dist: jsonschema<4.26,>=4.9
Requires-Dist: Pillow<12.2,>=10.3
Requires-Dist: pulpcore<3.115,>=3.63.0
Requires-Dist: PyYAML<7.0,>=6.0.2
Requires-Dist: semantic_version<2.11,>=2.9
Dynamic: license-file
